went/__init__.py
went/mapping.py
went-0.2.0.dist-info/DESCRIPTION.rst
went-0.2.0.dist-info/METADATA
went-0.2.0.dist-info/RECORD
went-0.2.0.dist-info/WHEEL
went-0.2.0.dist-info/metadata.json
went-0.2.0.dist-info/top_level.txt
