Metadata-Version: 2.0
Name: went
Version: 0.2.0
Summary: Tools for implementing a webmention enpoint.
Home-page: UNKNOWN
Author: fiatjaf
Author-email: fiatjaf@gmail.com
License: MIT
Platform: UNKNOWN
Requires-Dist: PyYAML (==3.11)
Requires-Dist: beautifulsoup4 (==4.3.2)
Requires-Dist: gunicorn (==19.2.1)
Requires-Dist: html5lib (==0.999)
Requires-Dist: mf2py (==0.2.4)
Requires-Dist: pyaml (==15.02.1)
Requires-Dist: redis (==2.10.3)
Requires-Dist: requests (==2.5.3)
Requires-Dist: six (==1.9.0)
Requires-Dist: wsgiref (==0.1.2)
Requires-Dist: html2text (==2015.2.18)
